BubbleTask/__init__.py
BubbleTask/__main__.py
BubbleTask/BubbleTask/BubbleApp.py
BubbleTask/BubbleTask/BubbleLib.py
BubbleTask/BubbleTask/BubbleRenderer.py
BubbleTask/BubbleTask/ColorPickerButton.py
BubbleTask/BubbleTask/DatePicker.py
BubbleTask/BubbleTask/NewTaskWindow.py
BubbleTask/BubbleTask/NotesFrame.py
BubbleTask/BubbleTask/ProjectTab.py
BubbleTask/BubbleTask/ProjectsTab.py
BubbleTask/BubbleTask/SettingsWindow.py
BubbleTask/BubbleTask/Spinbox.py
BubbleTask/BubbleTask/StartEndNameWindow.py
BubbleTask/BubbleTask/TasksFrame.py
BubbleTask/BubbleTask/TimeSelectionButton.py
BubbleTask/BubbleTask/ViewerTab.py
BubbleTask/BubbleTask/__init__.py
BubbleTask-0.0.6.dist-info/LICENSE
BubbleTask-0.0.6.dist-info/METADATA
BubbleTask-0.0.6.dist-info/WHEEL
BubbleTask-0.0.6.dist-info/top_level.txt
BubbleTask-0.0.6.dist-info/RECORD
