Metadata-Version: 2.1
Name: BubbleTask
Version: 0.0.6
Summary: Configurable, visual task-planning tool that lives on your desktop background.
Author-email: AndrewSpangler@users.noreply.github.com
Project-URL: Homepage, https://github.com/AndrewSpangler/BubbleTask/
Project-URL: Bug Tracker, https://github.com/AndrewSpangler/BubbleTask/issues
Classifier: Development Status :: 1 - Planning
Classifier: Environment :: Console
Classifier: License :: OSI Approved :: GNU General Public License v3 or later (GPLv3+)
Classifier: Natural Language :: English
Classifier: Operating System :: OS Independent
Classifier: Programming Language :: Python :: 3
Classifier: Programming Language :: Python :: 3.8
Classifier: Programming Language :: Python :: 3.9
Classifier: Programming Language :: Python :: 3.10
Requires-Python: >=3.8
License-File: LICENSE
Requires-Dist: tkcalendar
Requires-Dist: tkTimePicker
Requires-Dist: py-simple-ttk
Requires-Dist: pillow
